mcp_airtable/__init__.py
mcp_airtable/server.py
mcp_airtable-0.0.2.dist-info/METADATA
mcp_airtable-0.0.2.dist-info/WHEEL
mcp_airtable-0.0.2.dist-info/entry_points.txt
mcp_airtable-0.0.2.dist-info/top_level.txt
mcp_airtable-0.0.2.dist-info/RECORD
